{
  "spawnPattern": {
    "spawnGroupWaves": [
      {
        "possibleGroups": [
          {
            "characterDataContainerList": [
              {
                "characterData": "Shadewings"
              },
              {
                "characterData": "Darkwings"
              }
            ]
          }
        ]
      },
      {
        "possibleGroups": [
          {
            "characterDataContainerList": [
              {
                "characterData": "Shadewings"
              },
              {
                "characterData": "Shadewings",
                "requiredCovenant": "Ascension03MajorBattlesNewEnemies"
              },
              {
                "characterData": "Gilded Wing"
              }
            ]
          }
        ]
      },
      {
        "possibleGroups": [
          {
            "characterDataContainerList": [
              {
                "characterData": "Shadewings"
              },
              {
                "characterData": "Shadewings"
              },
              {
                "characterData": "Darkwings"
              }
            ]
          }
        ]
      },
      {
        "possibleGroups": [
          {
            "characterDataContainerList": [
              {
                "characterData": "Shadewings"
              },
              {
                "characterData": "Gilded Wing",
                "requiredCovenant": "Ascension01StrongerEnemies"
              },
              {
                "characterData": "Gilded Wing"
              }
            ]
          }
        ]
      },
      {
        "possibleGroups": [
          {
            "characterDataContainerList": [
              {
                "characterData": "Shadewings"
              },
              {
                "characterData": "Gilded Wing"
              },
              {
                "characterData": "Darkwings"
              }
            ]
          }
        ]
      },
      {
        "possibleGroups": [
          {
            "characterDataContainerList": [
              {
                "characterData": "Shadewings"
              },
              {
                "characterData": "Gilded Wing"
              },
              {
                "characterData": "Gilded Wing",
                "requiredCovenant": "Ascension03MajorBattlesNewEnemies"
              }
            ]
          }
        ]
      },
      {
        "possibleGroups": [
          {
            "characterDataContainerList": [
              {
                "characterData": "Shadewings"
              },
              {
                "characterData": "Darkwings"
              },
              {
                "characterData": "Steelwings"
              }
            ]
          }
        ]
      },
      {
        "possibleGroups": [
          {
            "characterDataContainerList": [
              {
                "characterData": "Shadewings"
              },
              {
                "characterData": "Darkwings"
              }
            ]
          }
        ]
      }
    ],
    "bossType": "SpawnPatternData.BossType.OuterTrainBoss",
    "bossCharacter": "Seraph the Temperant",
    "hardBossCharacter": "Seraph the Temperant Hard"
  },
  "battleName": "Seraph the Temperant",
  "battleDescription": "The end is near. This incarnation of Hell's greatest foe will <b>temper the strength of your units</b>. Only the truly determined can survive.",
  "difficulty": "ScenarioDifficulty.Boss",
  "enemyBlessingData": [
    "Enemy_SeraphSap"
  ],
  "battleTrackNameData": "BattleMusic_Seraph",
  "treasureCharacterPool": [

  ],
  "traitorUnitsPool": [

  ],
  "ftueCardDrawData": [

  ],
  "displayedEnemies": [

  ],
  "displayedEnemyOffsets": [

  ],
  "bossSpawnSFXCue": "Seraph_Intro",
  "backgroundData": "CaveBackgroundData",
  "name": "Level8FinalBossDebuffUnits"
}