{
  "spawnPattern": {
    "spawnGroupWaves": [
      {
        "possibleGroups": [
          {
            "characterDataContainerList": [
              {
                "characterData": "HordeT2DeathGivesAttack"
              },
              {
                "characterData": "HordeT2DeathGivesAttack"
              },
              {
                "characterData": "HordeT2DeathGivesAttack"
              },
              {
                "characterData": "HordeT2DeathGivesAttack"
              }
            ]
          }
        ]
      },
      {
        "possibleGroups": [
          {
            "characterDataContainerList": [
              {
                "characterData": "HeavyT2Basic"
              },
              {
                "characterData": "HordeT2DeathGivesAttack"
              },
              {
                "characterData": "HordeT2DeathGivesAttack"
              },
              {
                "characterData": "HordeT2DeathGivesAttack"
              },
              {
                "characterData": "HordeT2DeathGivesAttack"
              }
            ]
          }
        ]
      },
      {
        "possibleGroups": [
          {
            "characterDataContainerList": [
              {
                "characterData": "HordeT2DeathGivesAttack"
              },
              {
                "characterData": "HordeT2DeathGivesAttack"
              },
              {
                "characterData": "HordeT2DeathGivesAttack"
              },
              {
                "characterData": "HordeT2DeathGivesAttack",
                "requiredCovenant": "Ascension05MinorBattlesNewEnemies"
              },
              {
                "characterData": "ShieldGuardT2"
              }
            ]
          }
        ]
      },
      {
        "possibleGroups": [
          {
            "characterDataContainerList": [
              {
                "characterData": "HordeT2DeathGivesAttack"
              },
              {
                "characterData": "HordeT2DeathGivesAttack"
              },
              {
                "characterData": "HordeT2DeathGivesAttack",
                "requiredCovenant": "Ascension05MinorBattlesNewEnemies"
              },
              {
                "characterData": "ShieldGuardT2"
              },
              {
                "characterData": "ShieldGuardT2"
              }
            ]
          }
        ]
      },
      {
        "possibleGroups": [
          {
            "hasWaveMessage": true,
            "waveMessageKey": "ScenarioData_waveMessageKey-9f17d9103a0a7290-e63cc8bbd63736e4e839377fa340fff6-v2"
          }
        ]
      },
      {
        "possibleGroups": [
          {
            "characterDataContainerList": [
              {
                "characterData": "HordeT2DeathGivesAttack"
              },
              {
                "characterData": "Boss_Level5",
                "useBossCharacter": true
              },
              {
                "characterData": "ShieldGuardT1"
              }
            ]
          }
        ]
      }
    ]
  },
  "bossVariant": "Level5Bosses",
  "enemyBlessingData": [

  ],
  "battleTrackNameData": "",
  "minTreasureUnits": 1,
  "maxTreasureUnits": 1,
  "treasureCharacterPool": [
    "TreasureBagLvl2Gold"
  ],
  "traitorUnitsPool": [
    null
  ],
  "trials": {
    "listName": "T2Trials",
    "trialDatas": [
      null,
      null,
      null,
      null,
      null,
      null,
      null
    ]
  },
  "ftueCardDrawData": [

  ],
  "battleNameKey": "ScenarioData_battleNameKey-a44d782af40bb311-e63cc8bbd63736e4e839377fa340fff6-v2",
  "battleDescriptionKey": "ScenarioData_battleDescriptionKey-984d233833738f4f-e63cc8bbd63736e4e839377fa340fff6-v2",
  "displayedEnemies": [
    "HeavyT2Basic",
    "HordeT2DeathGivesAttack"
  ],
  "displayedEnemyOffsets": [

  ],
  "backgroundData": "CaveBackgroundData",
  "name": "Level5BattleHorde"
}