{
  "upgradeDescription": "[inert], [multistrike] 1, and '[feed]: Gain [spark] 1.'",
  "statusEffectUpgrades": [
    {
      "statusId": "VanillaStatusEffectIDs.Inert",
      "count": 1
    },
    {
      "statusId": "VanillaStatusEffectIDs.Multistrike",
      "count": 1
    }
  ],
  "triggerUpgrades": [
    {
      "description": "Gain [spark] 1.",
      "effects": [
        {
          "paramStatusEffects": [
            {
              "statusId": "VanillaStatusEffectIDs.Fuel",
              "count": 1
            }
          ],
          "effectStateName": "CardEffectAddStatusEffect",
          "targetMode": "TargetMode.Self",
          "targetTeamType": "Team.Type.None"
        }
      ],
      "trigger": "CharacterTriggerData.Trigger.OnFeed"
    }
  ],
  "hideUpgradeIconOnCard": true,
  "isUnitSynthesisUpgrade": true,
  "sourceSynthesisUnit": "Alloyed Construct",
  "linkedPactDuplicateRarity": "CollectableRarity.Rare"
}