{
  "name": "Dripfall",
  "overrideDescription": "[descend] a unit. Apply [dazed] [effect1.status0.power].",
  "effects": [
    {
      "effectStateName": "CardEffectBump",
      "targetMode": "TargetMode.DropTargetCharacter",
      "targetTeamType": "Team.Type.Heroes | Team.Type.Monsters",
      "paramInt": -1
    },
    {
      "paramStatusEffects": [
        {
          "statusId": "VanillaStatusEffectIDs.Dazed",
          "count": 1
        }
      ],
      "effectStateName": "CardEffectAddStatusEffect",
      "targetMode": "TargetMode.LastTargetedCharacters",
      "targetTeamType": "Team.Type.Heroes | Team.Type.Monsters"
    }
  ],
  "cardLoreTooltips": [
    "While Wax Drips are beneficial for those who refuse to melt, getting caught in the downfall can have violent consequences. Consequently, I've decided only to study them from a safe distance."
  ],
  "cost": 1,
  "cardType": "CardType.Spell",
  "targetless": false,
  "rarity": "CollectableRarity.Common",
  "linkedClass": "ClassRemnant",
  "initialKeyboardTarget": "CardInitialKeyboardTarget.FrontFriendly"
}