{
  "nameKey": "CardData_nameKey-63a790ceb1bcf0c8-705ea064154a2624a8e7af1aabc85bb1-v2",
  "cost": 1,
  "overrideDescriptionKey": "CardData_overrideDescriptionKey-4486d0ea967ad410-705ea064154a2624a8e7af1aabc85bb1-v2",
  "targetless": false,
  "effects": [
    {
      "effectStateName": "CardEffectDamage",
      "targetMode": 12,
      "targetTeamType": 3,
      "paramInt": 3,
      "statusEffectStackMultiplier": "rooted"
    },
    {
      "effectStateName": "CardEffectAddStatusEffect",
      "targetMode": 22,
      "targetTeamType": 3,
      "paramStatusEffects": [
        {
          "statusId": "poison",
          "count": 8
        }
      ]
    }
  ],
  "linkedClass": "ClassStygian",
  "cardLoreTooltipKeys": [
    "CardData_data-88daad22bf573de1-705ea064154a2624a8e7af1aabc85bb1-v2"
  ],
  "initialKeyboardTarget": 2,
  "name": "Flash Freeze"
}