{
  "m_Name": "MonsterSoothingSiren",
  "id": "cbcafb19-37b5-4a48-9fbc-52ae3668dad8",
  "nameKey": "CharacterData_nameKey-b3a8b8fdfefdf7df-2a61651727153fe4daa24e6730233a10-v2",
  "characterPrefabVariantRef": {
    "m_debugName": "Assets/GameData/characters/Character_Prefabs/AutoCreated/Character_MonsterDarkKnight.prefab",
    "m_AssetGUID": "f93ab447d2d58204cb8eaebc1856b56e"
  },
  "pactCrystalsRequiredCount": -1,
  "bypassPactCrystalsUpgradeDataList": [

  ],
  "size": 2,
  "blockVisualSizeIncrease": false,
  "health": 6,
  "canBeHealed": true,
  "isOuterTrainBoss": false,
  "validBossAttackPhase": 2,
  "isMiniboss": false,
  "deathType": 0,
  "canAttack": true,
  "ascendsTrainAutomatically": true,
  "attackDamage": 1,
  "animationController": {
    "m_FileID": 0,
    "m_PathID": 0
  },
  "attackTeleportsToDefender": true,
  "deathSlidesBackwards": true,
  "projectilePrefab": {
    "vfxPrefabLeft": {
      "m_FileID": 0,
      "m_PathID": 0
    },
    "vfxPrefabRight": {
      "m_FileID": 0,
      "m_PathID": 0
    },
    "spawnLocation": 0,
    "facing": 0
  },
  "impactVFX": {
    "vfxPrefabLeft": {
      "m_FileID": 0,
      "m_PathID": 0
    },
    "vfxPrefabRight": {
      "m_FileID": 0,
      "m_PathID": 0
    },
    "spawnLocation": 0,
    "facing": 0
  },
  "deathVFX": {
    "vfxPrefabLeft": {
      "m_FileID": 0,
      "m_PathID": 0
    },
    "vfxPrefabRight": {
      "m_FileID": 0,
      "m_PathID": 0
    },
    "spawnLocation": 0,
    "facing": 0
  },
  "bossSpellCastVFX": {
    "vfxPrefabLeft": {
      "m_FileID": 0,
      "m_PathID": 0
    },
    "vfxPrefabRight": {
      "m_FileID": 0,
      "m_PathID": 0
    },
    "spawnLocation": 0,
    "facing": 0
  },
  "bossRoomSpellCastVFX": {
    "vfxPrefabLeft": {
      "m_FileID": 0,
      "m_PathID": 0
    },
    "vfxPrefabRight": {
      "m_FileID": 0,
      "m_PathID": 0
    },
    "spawnLocation": 0,
    "facing": 0
  },
  "startingStatusEffects": [

  ],
  "statusEffectImmunities": [

  ],
  "triggers": [
    {
      "trigger": 19,
      "descriptionKey": "CharacterData_descriptionKey-1d6c6e05f3edc8cb-2a61651727153fe4daa24e6730233a10-v2",
      "additionalTextOnTriggerKey": "EmptyString-0000000000000000-00000000000000000000000000000000-v2",
      "displayEffectHintText": false,
      "hideTriggerTooltip": false,
      "effects": [
        {
          "effectStateName": "CardEffectAddStatusEffect",
          "targetMode": 2,
          "targetModeStatusEffectsFilter": [

          ],
          "targetModeHealthFilter": 0,
          "targetIgnoreBosses": false,
          "filterBasedOnMainSubClass": false,
          "copyModifiersFromSource": false,
          "ignoreTemporaryModifiersFromSource": false,
          "targetTeamType": 1,
          "targetCharacterSubtype": "SubtypesData_None",
          "targetCardType": 0,
          "targetCardSelectionMode": 0,
          "animToPlay": 0,
          "appliedToSelfVFX": {
            "vfxPrefabLeft": {
              "m_FileID": 0,
              "m_PathID": 0
            },
            "vfxPrefabRight": {
              "m_FileID": 0,
              "m_PathID": 0
            },
            "spawnLocation": 0,
            "facing": 0
          },
          "appliedVFX": {
            "vfxPrefabLeft": {
              "m_FileID": 0,
              "m_PathID": 0
            },
            "vfxPrefabRight": {
              "m_FileID": 0,
              "m_PathID": 0
            },
            "spawnLocation": 0,
            "facing": 0
          },
          "shouldTest": true,
          "useIntRange": false,
          "paramInt": 0,
          "additionalParamInt": 0,
          "paramStr": "",
          "paramBool": false,
          "paramSubtype": "SubtypesData_None",
          "paramMinInt": 0,
          "paramMaxInt": 0,
          "paramMultiplier": 1.0,
          "useStatusEffectStackMultiplier": false,
          "statusEffectStackMultiplier": "",
          "paramCharacterData": null,
          "paramAdditionalCharacterData": null,
          "paramCharacterDataPool": [

          ],
          "paramRoomData": null,
          "paramCardPool": [

          ],
          "paramCardFilter": null,
          "paramTrigger": 0,
          "paramStatusEffects": [
            {
              "statusId": "debuff",
              "count": 2
            }
          ],
          "paramCardUpgradeData": null,
          "paramTimingDelays": {
            "x": 0.0,
            "y": 0.0,
            "z": 0.0
          },
          "hideTooltip": false,
          "additionalTooltips": [

          ]
        }
      ]
    }
  ],
  "subtypeKeys": [
    "SubtypesData_Siren_727cf19f-3b27-4ad2-92ab-3552449e52da"
  ],
  "removeTriggersOnRelentlessChange": false,
  "bossActionGroups": [

  ],
  "characterSoundData": {
    "m_FileID": 0,
    "m_PathID": 0
  },
  "characterChatterData": {
    "m_FileID": 0,
    "m_PathID": 0
  },
  "characterLoreTooltipKeys": [

  ],
  "roomModifiers": [

  ],
  "name": "Archived Soothing Siren"
}