{
  "name": "Shattered Shell",
  "startingStatusEffects": [
    {
      "statusId": "VanillaStatusEffectIDs.Sweep",
      "count": 1
    }
  ],
  "triggers": [
    {
      "description": "+[effect0.upgrade.bonusdamage][attack].",
      "effects": [
        {
          "paramCardUpgradeData": {
            "bonusDamage": 3
          },
          "effectStateName": "CardEffectAddTempCardUpgradeToUnits",
          "targetMode": "TargetMode.Self",
          "targetTeamType": "Team.Type.None"
        }
      ],
      "trigger": "CharacterTriggerData.Trigger.OnKill"
    }
  ],
  "subtypes": [
    "Animus",
    "Chosen"
  ],
  "characterLoreTooltips": [
    "When Husk Hermits grow too large for their already restrictive shell, they keep the shattered steel pieces for offensive use. Against my wishes, the Channelers have hoarded Pyre shards to further enhance the power of these creatures."
  ],
  "size": 2,
  "health": 10,
  "attackDamage": 3
}