{
  "name": "A Simple Plan",
  "description": "Non-Champion units cost +2[ember]. Start with <b>Sketches of Salvation</b>.",
  "effects": [
    {
      "relicEffectClassName": "RelicEffectAddRelicStartOfRun",
      "paramSourceTeam": "Team.Type.None",
      "paramTrigger": "CharacterTriggerData.Trigger.OnDeath",
      "paramTargetMode": "TargetMode.FrontInRoom",
      "paramCardType": "CardType.Spell",
      "paramRelic": "RandomUnitEveryFloor"
    },
    {
      "relicEffectClassName": "RelicEffectModifyCardTypeCost",
      "paramSourceTeam": "Team.Type.None",
      "paramInt": 2,
      "paramTrigger": "CharacterTriggerData.Trigger.OnDeath",
      "paramTargetMode": "TargetMode.FrontInRoom",
      "paramCardType": "CardType.Monster",
      "paramRelic": "RandomUnitEveryFloor"
    }
  ],
  "boonValue": -3,
  "tags": [
    "embercost"
  ]
}