{
  "name": "Early Lead",
  "description": "Start with <b>Improved Firebox</b> and <b>Lost Luggage</b>.",
  "effects": [
    {
      "relicEffectClassName": "RelicEffectAddRelicStartOfRun",
      "paramSourceTeam": "Team.Type.None",
      "paramTrigger": "CharacterTriggerData.Trigger.OnDeath",
      "paramTargetMode": "TargetMode.FrontInRoom",
      "paramCardType": "CardType.Spell",
      "paramRelic": "EmberAtBattleStart"
    },
    {
      "relicEffectClassName": "RelicEffectAddRelicStartOfRun",
      "paramSourceTeam": "Team.Type.None",
      "paramTrigger": "CharacterTriggerData.Trigger.OnDeath",
      "paramTargetMode": "TargetMode.FrontInRoom",
      "paramCardType": "CardType.Spell",
      "paramRelic": "U3DrawToMaxStartOfCombat"
    }
  ],
  "boonValue": 4,
  "requiredDLC": "ShinyShoe.DLC.Hellforged"
}