{
  "m_Name": "MultistrikePyre",
  "id": "3f33b066-6ec4-4430-8f6e-7636fbd1706c",
  "nameKey": "MutatorData_nameKey-c1dbc13d6d1b0520-eea9d789705395f4096e87d2e18724a8-v2",
  "descriptionKey": "MutatorData_descriptionKey-9a8ba15971e1eb3a-eea9d789705395f4096e87d2e18724a8-v2",
  "relicActivatedKey": "EmptyString-0000000000000000-00000000000000000000000000000000-v2",
  "relicLoreTooltipKeys": [

  ],
  "relicLoreTooltipStyle": 0,
  "icon": {
    "m_FileID": 0,
    "m_PathID": 2305
  },
  "divineVariant": false,
  "effects": [
    {
      "relicEffectClassName": "RelicEffectAddStatusEffectOnSpawn",
      "paramSourceTeam": 2,
      "paramInt": 0,
      "paramFloat": 0.0,
      "paramUseIntRange": false,
      "paramMinInt": 0,
      "paramMaxInt": 0,
      "paramString": "",
      "paramCharacterSubtype": "SubtypesData_Pyre",
      "paramExcludeCharacterSubtypes": [

      ],
      "paramSpecialCharacterType": 0,
      "paramBool": false,
      "paramStatusEffects": [
        {
          "statusId": "multistrike",
          "count": 1
        }
      ],
      "paramCardEffects": [

      ],
      "paramTrigger": 0,
      "paramTargetMode": 0,
      "paramRoomData": null,
      "paramCardType": 0,
      "paramCardPool": [

      ],
      "paramRandomChampionPool": [

      ],
      "paramEnhancerPool": [

      ],
      "paramCardFilter": null,
      "paramCardSetBuilder": null,
      "paramRelic": null,
      "paramReward": null,
      "appliedVfx": {
        "vfxPrefabLeft": {
          "m_FileID": 0,
          "m_PathID": 0
        },
        "vfxPrefabRight": {
          "m_FileID": 0,
          "m_PathID": 0
        },
        "spawnLocation": 0,
        "facing": 0
      },
      "tooltipTitleKey": "EmptyString-0000000000000000-00000000000000000000000000000000-v2",
      "tooltipBodyKey": "EmptyString-0000000000000000-00000000000000000000000000000000-v2",
      "additionalTooltips": [

      ],
      "triggerTooltipsSuppressed": false,
      "paramCharacters": [

      ],
      "effectConditions": [

      ],
      "sourceCardTraitParam": "",
      "targetCardTraitParam": "",
      "traits": [

      ],
      "excludedTraits": [

      ],
      "triggers": [

      ],
      "cardTriggers": [

      ],
      "paramCardUpgradeData": null
    }
  ],
  "boonValue": 3,
  "disableInDailyChallenges": false,
  "requiredDLC": 0,
  "tags": [
    "enemiesfragileatpyre"
  ],
  "name": "Multi-Pyre"
}