{
  "m_Name": "ShuffleUnits",
  "id": "afcb1af2-64f5-4887-9f7b-7e509e326604",
  "nameKey": "MutatorData_nameKey-5b14b4488255c95a-93a3267f22ffa5041b7d7c7d55f074fb-v2",
  "descriptionKey": "MutatorData_descriptionKey-0888df5af862d7f2-93a3267f22ffa5041b7d7c7d55f074fb-v2",
  "relicActivatedKey": "MutatorData_relicActivatedKey-971f40e16d242b32-93a3267f22ffa5041b7d7c7d55f074fb-v2",
  "relicLoreTooltipKeys": [

  ],
  "relicLoreTooltipStyle": 0,
  "icon": {
    "m_FileID": 0,
    "m_PathID": 2210
  },
  "divineVariant": false,
  "effects": [
    {
      "relicEffectClassName": "RelicEffectShuffleUnitsEndOfTurn",
      "paramSourceTeam": 0,
      "paramInt": 0,
      "paramFloat": 0.0,
      "paramUseIntRange": false,
      "paramMinInt": 0,
      "paramMaxInt": 0,
      "paramString": "",
      "paramCharacterSubtype": "SubtypesData_None",
      "paramExcludeCharacterSubtypes": [

      ],
      "paramSpecialCharacterType": 0,
      "paramBool": false,
      "paramStatusEffects": [

      ],
      "paramCardEffects": [

      ],
      "paramTrigger": 0,
      "paramTargetMode": 0,
      "paramRoomData": null,
      "paramCardType": 0,
      "paramCardPool": [

      ],
      "paramRandomChampionPool": [

      ],
      "paramEnhancerPool": [

      ],
      "paramCardFilter": null,
      "paramCardSetBuilder": null,
      "paramRelic": null,
      "paramReward": null,
      "appliedVfx": {
        "vfxPrefabLeft": {
          "m_FileID": 0,
          "m_PathID": 0
        },
        "vfxPrefabRight": {
          "m_FileID": 0,
          "m_PathID": 0
        },
        "spawnLocation": 0,
        "facing": 0
      },
      "tooltipTitleKey": "EmptyString-0000000000000000-00000000000000000000000000000000-v2",
      "tooltipBodyKey": "EmptyString-0000000000000000-00000000000000000000000000000000-v2",
      "additionalTooltips": [

      ],
      "triggerTooltipsSuppressed": false,
      "paramCharacters": [

      ],
      "effectConditions": [

      ],
      "sourceCardTraitParam": "",
      "targetCardTraitParam": "",
      "traits": [

      ],
      "excludedTraits": [

      ],
      "triggers": [

      ],
      "cardTriggers": [

      ],
      "paramCardUpgradeData": null
    }
  ],
  "boonValue": -1,
  "disableInDailyChallenges": false,
  "requiredDLC": 0,
  "tags": [

  ],
  "name": "Musical Chairs"
}