{
  "name": "Ninja Training",
  "description": "Minor bosses enter with [stealth] 5.",
  "effects": [
    {
      "paramStatusEffects": [
        {
          "statusId": "VanillaStatusEffectIDs.Stealth",
          "count": 5
        }
      ],
      "relicEffectClassName": "RelicEffectAddStatusEffectOnSpawn",
      "paramSourceTeam": "Team.Type.Heroes",
      "paramCharacterSubtype": "SubtypesData_Boss",
      "paramTrigger": "CharacterTriggerData.Trigger.OnDeath",
      "paramTargetMode": "TargetMode.FrontInRoom",
      "paramCardType": "CardType.Spell"
    }
  ],
  "boonValue": -3,
  "tags": [
    "enemyeffect"
  ]
}