{
  "m_Name": "FriendlySapPlusAttack",
  "id": "95cd7890-fa1c-4f27-8f38-b2d27b1ea8ad",
  "nameKey": "MutatorData_nameKey-48026580df536737-e214c064807a961438844f9fa1b19eb8-v2",
  "descriptionKey": "MutatorData_descriptionKey-db010ddcb94ba5da-e214c064807a961438844f9fa1b19eb8-v2",
  "relicActivatedKey": "EmptyString-0000000000000000-00000000000000000000000000000000-v2",
  "relicLoreTooltipKeys": [

  ],
  "relicLoreTooltipStyle": 0,
  "icon": {
    "m_FileID": 0,
    "m_PathID": 2080
  },
  "divineVariant": false,
  "effects": [
    {
      "relicEffectClassName": "RelicEffectModifyCardAttack",
      "paramSourceTeam": 2,
      "paramInt": 10,
      "paramFloat": 0.0,
      "paramUseIntRange": false,
      "paramMinInt": 0,
      "paramMaxInt": 0,
      "paramString": "",
      "paramCharacterSubtype": "SubtypesData_None",
      "paramExcludeCharacterSubtypes": [

      ],
      "paramSpecialCharacterType": 0,
      "paramBool": false,
      "paramStatusEffects": [
        {
          "statusId": "debuff",
          "count": 7
        }
      ],
      "paramCardEffects": [

      ],
      "paramTrigger": 0,
      "paramTargetMode": 0,
      "paramRoomData": null,
      "paramCardType": 1,
      "paramCardPool": [

      ],
      "paramRandomChampionPool": [

      ],
      "paramEnhancerPool": [

      ],
      "paramCardFilter": null,
      "paramCardSetBuilder": null,
      "paramRelic": null,
      "paramReward": null,
      "appliedVfx": {
        "vfxPrefabLeft": {
          "m_FileID": 0,
          "m_PathID": 0
        },
        "vfxPrefabRight": {
          "m_FileID": 0,
          "m_PathID": 0
        },
        "spawnLocation": 0,
        "facing": 0
      },
      "tooltipTitleKey": "EmptyString-0000000000000000-00000000000000000000000000000000-v2",
      "tooltipBodyKey": "EmptyString-0000000000000000-00000000000000000000000000000000-v2",
      "additionalTooltips": [

      ],
      "triggerTooltipsSuppressed": false,
      "paramCharacters": [

      ],
      "effectConditions": [

      ],
      "sourceCardTraitParam": "",
      "targetCardTraitParam": "",
      "traits": [

      ],
      "excludedTraits": [

      ],
      "triggers": [

      ],
      "cardTriggers": [

      ],
      "paramCardUpgradeData": null
    },
    {
      "relicEffectClassName": "RelicEffectAddStatusEffectOnSpawn",
      "paramSourceTeam": 2,
      "paramInt": -1,
      "paramFloat": 0.0,
      "paramUseIntRange": false,
      "paramMinInt": 0,
      "paramMaxInt": 0,
      "paramString": "",
      "paramCharacterSubtype": "SubtypesData_None",
      "paramExcludeCharacterSubtypes": [

      ],
      "paramSpecialCharacterType": 0,
      "paramBool": false,
      "paramStatusEffects": [
        {
          "statusId": "debuff",
          "count": 7
        }
      ],
      "paramCardEffects": [

      ],
      "paramTrigger": 0,
      "paramTargetMode": 0,
      "paramRoomData": null,
      "paramCardType": 0,
      "paramCardPool": [

      ],
      "paramRandomChampionPool": [

      ],
      "paramEnhancerPool": [

      ],
      "paramCardFilter": null,
      "paramCardSetBuilder": null,
      "paramRelic": null,
      "paramReward": null,
      "appliedVfx": {
        "vfxPrefabLeft": {
          "m_FileID": 0,
          "m_PathID": 0
        },
        "vfxPrefabRight": {
          "m_FileID": 0,
          "m_PathID": 0
        },
        "spawnLocation": 0,
        "facing": 0
      },
      "tooltipTitleKey": "EmptyString-0000000000000000-00000000000000000000000000000000-v2",
      "tooltipBodyKey": "EmptyString-0000000000000000-00000000000000000000000000000000-v2",
      "additionalTooltips": [

      ],
      "triggerTooltipsSuppressed": false,
      "paramCharacters": [

      ],
      "effectConditions": [

      ],
      "sourceCardTraitParam": "",
      "targetCardTraitParam": "",
      "traits": [

      ],
      "excludedTraits": [

      ],
      "triggers": [

      ],
      "cardTriggers": [

      ],
      "paramCardUpgradeData": {
        "m_Name": "Plus10Attack",
        "id": "6d9f8b4d-8be0-4bd1-bd7e-edff5b557a31",
        "upgradeTitleKey": "EmptyString-0000000000000000-00000000000000000000000000000000-v2",
        "upgradeDescriptionKey": "EmptyString-0000000000000000-00000000000000000000000000000000-v2",
        "upgradeNotificationKey": "EmptyString-0000000000000000-00000000000000000000000000000000-v2",
        "upgradeIcon": {
          "m_FileID": 0,
          "m_PathID": 0
        },
        "hideUpgradeIconOnCard": false,
        "useUpgradeHighlightTextTags": true,
        "isUnitSynthesisUpgrade": false,
        "isUnique": false,
        "sourceSynthesisUnit": null,
        "linkedPactDuplicateRarity": 4,
        "bonusDamage": 10,
        "bonusHP": 0,
        "costReduction": 0,
        "xCostReduction": 0,
        "bonusHeal": 0,
        "bonusSize": 0,
        "statusEffectUpgrades": [

        ],
        "traitDataUpgrades": [

        ],
        "removeTraitUpgrades": [

        ],
        "triggerUpgrades": [

        ],
        "cardTriggerUpgrades": [

        ],
        "roomModifierUpgrades": [

        ],
        "filters": [

        ],
        "upgradesToRemove": [

        ]
      }
    }
  ],
  "boonValue": 0,
  "disableInDailyChallenges": false,
  "requiredDLC": 1,
  "tags": [
    "friendlyeffect"
  ],
  "name": "Slow and Steady"
}