{
  "name": "Ember Stasis",
  "description": "Playing a [blight] card deals [effect0.power] damage to the front enemy unit.",
  "relicLoreTooltips": [
    "Ember is rarely observed in between states of living and dying, making it challenging to learn what destroys its lifeforce. The fragments are volatile things, guided entirely by how much they like their owner."
  ],
  "effects": [
    {
      "relicEffectClassName": "RelicEffectDamageOnCardPlayed",
      "paramSourceTeam": "Team.Type.Heroes",
      "paramInt": 120,
      "paramTrigger": "CharacterTriggerData.Trigger.OnDeath",
      "paramTargetMode": "TargetMode.FrontInRoom",
      "paramCardType": "CardType.Blight"
    }
  ],
  "relicLoreTooltipStyle": "RelicData.RelicLoreTooltipStyle.Herzal",
  "rarity": "CollectableRarity.Common",
  "fromStoryEvent": true
}